photon/__init__.py
photon/config.py
photon/provisioner.py
photon/shell.py
python_photon-1.0.2.dist-info/DESCRIPTION.rst
python_photon-1.0.2.dist-info/METADATA
python_photon-1.0.2.dist-info/RECORD
python_photon-1.0.2.dist-info/WHEEL
python_photon-1.0.2.dist-info/entry_points.txt
python_photon-1.0.2.dist-info/metadata.json
python_photon-1.0.2.dist-info/pbr.json
python_photon-1.0.2.dist-info/top_level.txt
