Metadata-Version: 2.0
Name: python-photon
Version: 1.0.2
Summary: A data driven tool to run workflows using Ansible.
Home-page: https://github.com/metacloud/photon
Author: UNKNOWN
Author-email: UNKNOWN
License: MIT
Platform: UNKNOWN
Classifier: Environment :: Console
Classifier: Intended Audience :: Information Technology
Classifier: Intended Audience :: System Administrators
Classifier: License :: OSI Approved :: MIT License
Classifier: Operating System :: POSIX :: Linux
Classifier: Programming Language :: Python
Classifier: Programming Language :: Python :: 2
Classifier: Programming Language :: Python :: 2.7
Requires-Dist: click
Requires-Dist: colorama
Requires-Dist: pbr
Requires-Dist: pyyaml
Requires-Dist: sh
